dvg_pid_controller.py
dvg_pid_controller-2.2.0.dist-info/AUTHORS.rst
dvg_pid_controller-2.2.0.dist-info/LICENSE.txt
dvg_pid_controller-2.2.0.dist-info/METADATA
dvg_pid_controller-2.2.0.dist-info/WHEEL
dvg_pid_controller-2.2.0.dist-info/top_level.txt
dvg_pid_controller-2.2.0.dist-info/RECORD
