Metadata-Version: 2.1
Name: dvg-pid-controller
Version: 2.2.0
Summary: PID controller with integral-windup & derivative-kick prevention and bumpless manual-to-auto-mode transfer.
Home-page: https://github.com/Dennis-van-Gils/python-dvg-pid-controller
Author: Dennis van Gils
Author-email: vangils.dennis@gmail.com
License: MIT
Project-URL: Issue Tracker, https://github.com/Dennis-van-Gils/python-dvg-pid-controller/issues
Keywords: PID,feedback,controller,automation,laboratory,science
Classifier: Development Status :: 5 - Production/Stable
Classifier: License :: OSI Approved :: MIT License
Classifier: Intended Audience :: Developers
Classifier: Intended Audience :: Science/Research
Classifier: Operating System :: OS Independent
Classifier: Programming Language :: Python
Classifier: Programming Language :: Python :: 3
Classifier: Topic :: Scientific/Engineering 
Classifier: Topic :: Scientific/Engineering :: Electronic Design Automation (EDA)
Classifier: Topic :: Scientific/Engineering :: Physics
Requires-Python: >=3.6
License-File: LICENSE.txt
License-File: AUTHORS.rst
Requires-Dist: numpy <3.0,>=1.15
Requires-Dist: dvg-debug-functions ~=2.1
